Metadata-Version: 2.3
Name: mcp-server-kenxue
Version: 0.1.0
Summary: Add your description here
Requires-Dist: mcp[cli]>=1.24.0
Requires-Python: >=3.11
